muller_eot/__init__.py
muller_eot/calculate_eot.py
muller_eot/eotClass.py
muller_eot/error_handling.py
muller_eot/helper_function.py
muller_eot-1.4.3.dist-info/LICENSE
muller_eot-1.4.3.dist-info/METADATA
muller_eot-1.4.3.dist-info/WHEEL
muller_eot-1.4.3.dist-info/top_level.txt
muller_eot-1.4.3.dist-info/RECORD
