Metadata-Version: 2.1
Name: muller-eot
Version: 1.4.3
Summary: A Python package for M. Müller implementation of the 'Equation of Time - Problem in Astronomy' to calculate EOT and the effect of eccentricity/obliquity
Author-email: Cora Schneck <cyschneck@gmail.com>
License: MIT License
Project-URL: Repository, https://github.com/cyschneck/Muller-EOT
Project-URL: Issues, https://github.com/cyschneck/Muller-EOT/issues
Keywords: astronomy,python,eot,equation of time,eccentricity,obliquity,orbital dynamics
Classifier: Development Status :: 4 - Beta
Classifier: Intended Audience :: Developers
Classifier: Intended Audience :: Education
Classifier: Intended Audience :: Science/Research
Classifier: License :: OSI Approved :: MIT License
Classifier: Programming Language :: Python
Classifier: Programming Language :: Python :: 3
Classifier: Programming Language :: Python :: 3.10
Classifier: Programming Language :: Python :: 3.11
Classifier: Programming Language :: Python :: 3.12
Classifier: Intended Audience :: Education
Classifier: Intended Audience :: Science/Research
Classifier: Topic :: Scientific/Engineering :: Physics
Classifier: Topic :: Scientific/Engineering :: Visualization
Classifier: Topic :: Scientific/Engineering :: Astronomy
Requires-Python: >3.9
License-File: LICENSE
Requires-Dist: matplotlib
Requires-Dist: numpy
